odoo/addons/purchase_comment_template/README.rst
odoo/addons/purchase_comment_template/__init__.py
odoo/addons/purchase_comment_template/__manifest__.py
odoo/addons/purchase_comment_template/i18n/de.po
odoo/addons/purchase_comment_template/i18n/es.po
odoo/addons/purchase_comment_template/i18n/fr.po
odoo/addons/purchase_comment_template/i18n/it.po
odoo/addons/purchase_comment_template/i18n/purchase_comment_template.pot
odoo/addons/purchase_comment_template/models/__init__.py
odoo/addons/purchase_comment_template/models/purchase_order.py
odoo/addons/purchase_comment_template/readme/CONTRIBUTORS.md
odoo/addons/purchase_comment_template/readme/DESCRIPTION.md
odoo/addons/purchase_comment_template/readme/INSTALL.md
odoo/addons/purchase_comment_template/security/ir.model.access.csv
odoo/addons/purchase_comment_template/static/description/icon.png
odoo/addons/purchase_comment_template/static/description/index.html
odoo/addons/purchase_comment_template/tests/__init__.py
odoo/addons/purchase_comment_template/tests/test_purchase_order_report.py
odoo/addons/purchase_comment_template/views/base_comment_template_view.xml
odoo/addons/purchase_comment_template/views/purchase_order_view.xml
odoo/addons/purchase_comment_template/views/report_purchaseorder.xml
odoo/addons/purchase_comment_template/views/report_quotation.xml
odoo_addon_purchase_comment_template-18.0.1.0.2.2.dist-info/METADATA
odoo_addon_purchase_comment_template-18.0.1.0.2.2.dist-info/WHEEL
odoo_addon_purchase_comment_template-18.0.1.0.2.2.dist-info/top_level.txt
odoo_addon_purchase_comment_template-18.0.1.0.2.2.dist-info/RECORD
