Metadata-Version: 2.1
Name: odoo-addon-purchase_comment_template
Version: 18.0.1.0.2.2
Requires-Python: >=3.10
Requires-Dist: odoo-addon-base_comment_template==18.0.*
Requires-Dist: odoo==18.0.*
Summary: Comments texts templates on Purchase documents
Home-page: https://github.com/OCA/purchase-reporting
License: AGPL-3
Author: ForgeFlow, Odoo Community Association (OCA)
Author-email: support@odoo-community.org
Classifier: Programming Language :: Python
Classifier: Framework :: Odoo
Classifier: Framework :: Odoo :: 18.0
Classifier: License :: OSI Approved :: GNU Affero General Public License v3
